pg_db/__init__.py
pg_db/db.py
pg_db-1.2.dist-info/LICENSE
pg_db-1.2.dist-info/METADATA
pg_db-1.2.dist-info/WHEEL
pg_db-1.2.dist-info/top_level.txt
pg_db-1.2.dist-info/RECORD
